bat/__init__.py
bat/__main__.py
bat/_main.py
bat/apis/__init__.py
bat/apis/deepapi.py
bat/apis/google.py
bat/apis/imagga.py
bat/attacks/__init__.py
bat/attacks/bandits_attack.py
bat/attacks/base_attack.py
bat/attacks/simba_attack.py
bat/attacks/square_attack.py
bat/examples/__init__.py
bat/examples/bandits_attack_deepapi.py
bat/examples/simba_attack_deepapi.py
bat/examples/square_attack_deepapi.py
bat/utils/__init__.py
bat/utils/proj_lp.py
blackbox_adversarial_toolbox-0.1.2.dist-info/LICENSE
blackbox_adversarial_toolbox-0.1.2.dist-info/METADATA
blackbox_adversarial_toolbox-0.1.2.dist-info/WHEEL
blackbox_adversarial_toolbox-0.1.2.dist-info/entry_points.txt
blackbox_adversarial_toolbox-0.1.2.dist-info/top_level.txt
blackbox_adversarial_toolbox-0.1.2.dist-info/RECORD
