Metadata-Version: 2.1
Name: blackbox-adversarial-toolbox
Version: 0.1.2
Summary: Black-box Adversarial Toolbox (BAT) - Python Library for Deep Learning Security
Home-page: https://github.com/wuhanstudio/blackbox-adversarial-toolbox
Author: wuhanstudio
Author-email: wuhanstudio <wuhanstudios@gmail.com>
Maintainer: wuhanstudio
Maintainer-email: wuhanstudio <wuhanstudios@gmail.com>
License: MIT License
Project-URL: Homepage, https://github.com/wuhanstudio/blackbox-adversarial-toolbox
Project-URL: Bug Tracker, https://github.com/wuhanstudio/blackbox-adversarial-toolbox/issues
Classifier: Intended Audience :: Science/Research
Classifier: License :: OSI Approved :: MIT License
Classifier: Programming Language :: Python :: 3.6
Classifier: Programming Language :: Python :: 3.7
Classifier: Programming Language :: Python :: 3.8
Classifier: Programming Language :: Python :: 3.9
Classifier: Topic :: Scientific/Engineering :: Artificial Intelligence
Requires-Python: >=3.6
License-File: LICENSE
Requires-Dist: numpy (>=1.18.0)
Requires-Dist: scipy (>=1.4.1)
Requires-Dist: scikit-learn (>=0.22.2)
Requires-Dist: pillow
Requires-Dist: requests
Requires-Dist: tqdm
Requires-Dist: six
Requires-Dist: setuptools
Requires-Dist: click
Requires-Dist: google-cloud-vision
Requires-Dist: validators
